[
  {
    "newspaper": "ND Mais",
    "title": "Auditoria nacional reconhece o serviço de 12 cartórios de SC entre os melhores do país",
    "url": "https://ndmais.com.br/cidadania/auditoria-nacional-reconhece-o-servico-de-12-cartorios-de-sc-entre-os-melhores-do-pais/",
    "date": "17/12/2024 ÀS 10H09",
    "cities": [],
    "people": [
      "Rogerio Bacellar",
      "Anoreg BR",
      "Otávio Margarida",
      "ProtestoBalneário Camboriú2º Ofício de Registro de ImóveisCriciúma1°"
    ],
    "organizations": [
      "CNJ",
      "Conselho Nacional de Justiça",
      "PQTA",
      "Associação dos Notários e Registradores do Brasil",
      "APCER Brasil",
      "Associação Portuguesa de Certificação",
      "CNJ",
      "Conselho Nacional de Justiça).“Há",
      "Selo Digital Fiscalizador",
      "CNJ",
      "SCJoinvilleRegistro de ImóveisBarra VelhaOfício de Registro de ImóveisSão JoséTabelionato de Notas"
    ],
    "fraud": [
      "auditoria"
    ],
    "value": null,
    "prosecutor": null
  },
  {
    "newspaper": "Diário do Sul",
    "title": "PEDRO HERMÍNIO\n\t\t\t\t\t\t\t\t\t\t\tOs males da corrupção",
    "url": "https://diariodosul.com.br/colunistas/pedro-herminio/os-males-da-corrupcao-36010",
    "date": null,
    "cities": [],
    "people": [
      "Gaecos",
      "Pitágoras",
      "Ltda",
      "Machado de Assis"
    ],
    "organizations": [
      "Dia Internacional de Combate à Corrupção",
      "Lava Jato",
      "Educação fiscal\n\n",
      "Programa Nacional de Educação Fiscal",
      "Administração Tributária"
    ],
    "fraud": [
      "corrupção"
    ],
    "value": null,
    "prosecutor": null
  },
  {
    "newspaper": "SCC SBT",
    "title": "Roberto Azevedo\n            \n                Justiça Federal nega o pedido de suspensão da federalização do Porto de Itajaí",
    "url": "https://scc10.com.br/colunistas/roberto-azevedo/justica-federal-nega-o-pedido-de-suspensao-da-federalizacao-do-porto-de-itajai/",
    "date": "17/12/2024 12h48 • Atualizado há 50 segundos",
    "cities": [],
    "people": [
      "Moser Vhoss",
      "deputado",
      "PL",
      "Jorginho Mello",
      "Silvio Costa Filho",
      "ex-superintendente",
      "Décio Lima",
      "João Paulo Tavares",
      "João Paulo",
      "Instagram"
    ],
    "organizations": [
      "Convênio de Delegação",
      "Porto de Itajaí",
      "Foro Metropolitano da Foz do Rio Itajaí-Açú",
      "Porto de Itajaí",
      "Comissão de Viação e Transportes da Câmara",
      "Sebrae",
      "Porto de Itajaí",
      "PT",
      "Tribunal Regional Federal da 4ª Região",
      "TRF-4",
      "Threads"
    ],
    "fraud": [
      "justiça federal"
    ],
    "value": null,
    "prosecutor": null
  }
]